expect.py
xpect-3.1.1.dist-info/DESCRIPTION.rst
xpect-3.1.1.dist-info/METADATA
xpect-3.1.1.dist-info/RECORD
xpect-3.1.1.dist-info/WHEEL
xpect-3.1.1.dist-info/metadata.json
xpect-3.1.1.dist-info/top_level.txt
