Metadata-Version: 2.0
Name: xpect
Version: 3.1.1
Summary: Programmed dialogue with interactive streams.
Home-page: https://github.com/eerimoq/expect
Author: Erik Moqvist
Author-email: erik.moqvist@gmail.com
License: MIT
Keywords: expect
Platform: UNKNOWN
Classifier: License :: OSI Approved :: MIT License
Classifier: Programming Language :: Python :: 2
Classifier: Programming Language :: Python :: 3
